tdfs4ds/__init__.py
tdfs4ds/datasets.py
tdfs4ds/data/curves.csv
tdfs4ds/data/logo/tdfs4ds_logo.png
tdfs4ds/data/logo/teradata_sym_rgb_pos.png
tdfs4ds/data/logo/teradata_sym_rgb_wht_rev.png
tdfs4ds/dataset/__init__.py
tdfs4ds/dataset/dataset.py
tdfs4ds/dataset/dataset_catalog.py
tdfs4ds/feature_store/__init__.py
tdfs4ds/feature_store/entity_management.py
tdfs4ds/feature_store/feature_data_processing.py
tdfs4ds/feature_store/feature_query_retrieval.py
tdfs4ds/feature_store/feature_store_management.py
tdfs4ds/genai/__init__.py
tdfs4ds/genai/documentation.py
tdfs4ds/process_store/__init__.py
tdfs4ds/process_store/process_followup.py
tdfs4ds/process_store/process_query_administration.py
tdfs4ds/process_store/process_registration_management.py
tdfs4ds/process_store/process_store_catalog_management.py
tdfs4ds/utils/__init__.py
tdfs4ds/utils/filter_management.py
tdfs4ds/utils/info.py
tdfs4ds/utils/lineage.py
tdfs4ds/utils/query_management.py
tdfs4ds/utils/time_management.py
tdfs4ds/utils/visualization.py
tdfs4ds-0.2.5.4.dist-info/METADATA
tdfs4ds-0.2.5.4.dist-info/WHEEL
tdfs4ds-0.2.5.4.dist-info/top_level.txt
tdfs4ds-0.2.5.4.dist-info/RECORD
