Metadata-Version: 2.1
Name: tdfs4ds
Version: 0.2.5.4
Summary: A python package to simplify the usage of feature store using Teradata Vantage ...
Author: Denis Molin
Requires-Python: >=3.6
Requires-Dist: teradataml>=17.20
Requires-Dist: pandas
Requires-Dist: numpy
Requires-Dist: plotly
Requires-Dist: tqdm
Requires-Dist: networkx
Requires-Dist: sqlparse
Requires-Dist: langchain-openai
